example_sfg
pysfg
test
